feshttp/__init__.py
feshttp/_err_msg.py
feshttp/_json.py
feshttp/_requests.py
feshttp/_response.py
feshttp/aio_jrpclient.py
feshttp/aio_requests.py
feshttp/err.py
feshttp/sanic_jsonrpc.py
feshttp/sync_requests.py
feshttp/utils.py
feshttp-1.0.0b2.dist-info/LICENSE
feshttp-1.0.0b2.dist-info/METADATA
feshttp-1.0.0b2.dist-info/WHEEL
feshttp-1.0.0b2.dist-info/top_level.txt
feshttp-1.0.0b2.dist-info/RECORD
